<?xml version="1.0" encoding="UTF-8"?><i><chatserver>chat.bilibili.com</chatserver><chatid>88848845</chatid><mission>0</mission><maxlimit>1000</maxlimit><state>0</state><real_name>0</real_name><source>k-v</source><d p="144.04300,1,25,16777215,1603590718,0,3260ae74,40081054123425795">这个邮箱对不对</d><d p="199.85600,1,25,16777215,1603090440,0,367b7ec3,39818764424839171">你又不是斯坦福学生 操作啥</d><d p="62.08200,1,25,16777215,1602936114,0,e1f5ebe5,39737852831465477">matlab被禁了</d><d p="55.01100,1,25,16777215,1602936100,0,e1f5ebe5,39737845631418371">matlab被禁用了</d><d p="61.63900,1,25,16777215,1602920237,0,ae935aa1,39729528615993347">用matlab是不是也可以跳过了</d><d p="82.33300,1,25,16777215,1602154783,0,26f5da42,39328210329010183">用matalb可以吗</d><d p="26.50700,1,25,16777215,1601946621,0,510171b2,39219073514995715">2011年的啊。。。</d><d p="142.92700,1,25,15138834,1601179530,0,534c4391,38816897126367239">密玛不打玛就离谱哈哈哈哈</d><d p="62.34600,1,25,16777215,1601109598,0,e19c63ae,38780232304951303">这一部分可以跳了</d><d p="185.13100,1,25,16777215,1600927477,0,4682ab6e,38684748665061381">斯坦福 校友啊！</d><d p="69.47000,1,25,16777215,1599219877,0,a1f523aa,37789474581118983">同问 Python</d><d p="201.50000,1,25,16777215,1597568339,0,d83e47c4,36923593111109639">2011奶奶瞩目</d><d p="201.50000,1,25,16777215,1597568333,0,d83e47c4,36923589798658117">2011年瞩目</d><d p="30.83100,1,25,16777215,1597116231,0,221a2c24,36686558354997255">在哪</d><d p="189.01100,1,25,16777215,1595992097,0,efe78942,36097188375822343">学pytorch之前是不是应该学一些这个</d><d p="85.81400,1,25,16777215,1595833443,0,96285a6c,36014007525048323">没必要学这个的</d><d p="70.00300,1,25,16777215,1595833427,0,96285a6c,36013999228715011">现在都用python了</d><d p="28.73500,1,25,16777215,1595833376,0,96285a6c,36013972585447431">2011年的视频</d><d p="62.75600,1,25,16777215,1595683523,0,398d17d5,35935406480424963">一样练</d><d p="154.79300,1,25,16777215,1595581930,0,bac72358,35882142388453447">这个视频是啥意思啊</d><d p="180.41300,5,25,16646914,1595394075,0,f9b4c485,35783652296097795">hhhh</d><d p="104.65000,1,25,16777215,1595072083,0,4d5fbaf3,35614835921649669">Pytorch怎么做作业</d><d p="170.89900,1,25,16777215,1594991500,0,a213d333,35572587362779143">Python可以操作么</d><d p="71.72700,1,25,16777215,1594036007,0,879d771b,35071633828347907">两个都学不就行了</d><d p="212.39300,1,25,16777215,1593876264,0,231238f0,34987882524442629">coursera上有原版的课和作业</d><d p="42.48400,1,25,16777215,1593506535,0,948bcbf4,34794037671624707">python不行么</d><d p="139.29400,1,25,16777215,1593169215,0,5555c01d,34617185255555075">牛逼哦</d><d p="93.87700,1,25,16777215,1593169163,0,5555c01d,34617157962170373">运行特定文件</d><d p="207.51400,1,25,16777215,1592622878,0,2b929f7e,34330747049345031">讲究</d><d p="156.27700,5,25,16646914,1592281569,0,e932df8c,34151802670678019">就一个搭建的内网测试邮箱 不会真有人以为是他的邮箱吧？</d><d p="193.65500,1,25,16777215,1591484256,0,e7896841,33733780938686469">999</d><d p="142.19800,1,25,16777215,1591430928,0,f0c1079c,33705821895393287">这个只能跑octave程序吗</d><d p="24.88500,1,25,16777215,1590803610,0,1d31f4da,33376926846943235">加油</d><d p="58.29300,1,25,16777215,1589800260,0,f94816ff,32850882172813319">同问，用python</d><d p="30.30500,1,25,16777215,1589800218,0,f94816ff,32850860119162885">屏幕有点小</d><d p="75.74500,1,25,16777215,1589375402,0,b4ecf45,32628134416744455">github  cs229-assignment</d><d p="205.25800,1,25,16777215,1589164742,0,af6f7b74,32517687833264133">我用python做的，感觉比octave好弄一些</d><d p="206.55300,1,25,16777215,1587624831,0,80182cda,31710331099152387">这个是类似svn或者git的？</d><d p="165.13500,1,25,16777215,1587133269,0,ba32d8cd,31452611213262851">这是在干嘛呢</d><d p="0.57700,1,25,16777215,1586843800,0,67c39443,31300845768278023">25/112</d><d p="208.95600,1,25,16777215,1585982334,0,860dc453,30849189649842183">那我们怎么完成作业呀，在哪里找</d><d p="52.13300,1,25,16777215,1585716888,0,a09dce03,30710019236298759">用python的是不是可以跳过了？</d><d p="160.50400,1,25,16777215,1585408095,0,48d3dc48,30548122938114051">社工成功</d><d p="198.51300,1,25,16777215,1585148102,0,93c9d79e,30411811679371269">贴心</d><d p="38.20100,1,25,16777215,1584947541,0,34671227,30306660021436421">这些文件在那里</d><d p="80.31800,1,25,16777215,1584628151,0,b1f5d2a9,30139207679737861">就像是matlab</d><d p="147.88500,1,25,16777215,1584452580,0,8a75dc16,30047157863055363">成功盗号吴老师的斯坦福邮箱。</d><d p="140.54300,1,25,16777215,1583855556,0,22cc91d9,29734145259208707">你们提交了吗</d><d p="44.67100,1,25,16777215,1583855216,0,22cc91d9,29733967215198211">我毕业设计就是用matlab</d><d p="13.69100,1,25,16777215,1583855153,0,22cc91d9,29733933820674115">疫情结束我要找个工作</d><d p="5.82100,1,25,16777215,1583326524,0,92f5f475,29456780109021189">波尼个头</d><d p="6.44100,1,25,16777215,1581514289,0,653fa2e0,28506647012835330">卡了</d><d p="211.24200,1,25,16777215,1581412279,0,931b1527,28453164693323778">同问，现在还能做这个作业嘛</d><d p="189.41600,1,25,16777215,1580649787,0,ff8d5a87,28053399169138692">这个网站现在能用吗</d><d p="13.27100,1,25,16777215,1580538665,0,793c8fc8,27995139243245570">no</d><d p="1.31000,1,25,16777215,1580474576,0,608ee4eb,27961538341502976">菠萝菠萝，我是西瓜</d><d p="203.25700,1,25,16777215,1575249890,0,f91a5364,25222297980764160">我要去做作业了，各位拜拜</d><d p="189.93900,1,25,16777215,1573979725,0,86f394b,24556365521879042">讲究</d><d p="36.86600,1,25,16777215,1563265833,0,c598a0ec,18939200719028228">matlab好</d></i>