<?xml version="1.0" encoding="UTF-8"?><i><chatserver>chat.bilibili.com</chatserver><chatid>88849497</chatid><mission>0</mission><maxlimit>1500</maxlimit><state>0</state><real_name>0</real_name><source>k-v</source><d p="521.30900,1,25,16777215,1604416749,0,277481c8,40514132195147783">终于可以不用看字幕了</d><d p="354.09900,1,25,16777215,1604416615,0,277481c8,40514062003994631">小班的瑟瑟发抖</d><d p="437.80200,1,25,16777215,1603885217,0,2adb79d,40235456249462787">没明白的去看9-2</d><d p="399.45600,1,25,16777215,1603854821,0,3c863dec,40219520154468359">老年大学必修课程你们还不会？</d><d p="311.71300,1,25,16777215,1603854763,0,3c863dec,40219489598439431">俺也一样</d><d p="18.08800,1,25,16777215,1603851862,0,2e9368aa,40217968897949701">长龙哥，我也来了</d><d p="51.09100,1,25,16777215,1603798216,0,4bb2cd6,40189842797101059">山大计合</d><d p="11.48600,1,25,16777215,1603794505,0,7a531758,40187896948850695">长龙哥，我来了！！</d><d p="23.54200,1,25,16777215,1603718158,0,5f9d9f16,40147869445390341">计科</d><d p="410.34600,1,25,16777215,1603357766,0,9a2eaa63,39958920191016965">python 我不配拥有姓名吗</d><d p="1.49900,1,25,16777215,1603262237,0,3980e013,39908835151839235">嘤嘤嘤，看不懂</d><d p="715.12500,1,25,16777215,1603020375,0,1f63a2a9,39782030160429061">可视化识别率的变化，可以看出</d><d p="560.20400,1,25,16777215,1603020132,0,1f63a2a9,39781902696054787">正则化是防止过拟合</d><d p="385.31500,1,25,16777215,1602937497,0,5276cab8,39738578066997251">feed</d><d p="337.55500,1,25,16777215,1602937445,0,5276cab8,39738550995910663">m是数据的行数么</d><d p="177.96200,1,25,16777215,1602937253,0,5276cab8,39738450267602947">为什么是5个neutral</d><d p="8.05900,1,25,16777215,1602936882,0,5276cab8,39738255642984451">2020/10/17</d><d p="34.42700,1,25,16777215,1602410541,0,e40492ad,39462301444079619">哈工大土木工程</d><d p="744.91200,1,25,16777215,1602406232,0,d1744ae1,39460042064789511">真的没关系嘛</d><d p="446.78300,1,25,16777215,1602313301,0,4fc498ce,39411319775952903">a</d><d p="33.23100,1,25,16777215,1601987694,0,af6cc664,39240607819366407">英语专业，听说这课练习口语不错，坚持到这了，加油</d><d p="770.19200,1,25,16777215,1601889808,0,3d44b8aa,39189287039139847">这个老师好好啊</d><d p="69.26400,1,25,16707842,1601888611,0,461be825,39188659524075527">一天半看到这了</d><d p="107.93600,1,25,16777215,1601883305,0,51d4da87,39185877558099973">2020/10/5</d><d p="25.52800,1,25,16777215,1601087088,0,8bbe7000,38768430672248835">遥感</d><d p="778.48900,1,25,16777215,1601023667,0,d610e91e,38735179934597125">That's actually perfectly ok</d><d p="773.07700,1,25,16777215,1601023606,0,d610e91e,38735147692982277">太谦虚嘞</d><d p="571.51200,1,25,16777215,1599942661,0,e9d88a99,38168421332942853">hello</d><d p="335.75800,1,25,16777215,1598719263,0,3df82069,37527008633683971">高二瑟瑟发抖</d><d p="272.71000,1,25,16777215,1598719160,0,3df82069,37526954431741959">不想靠才华吃饭了 我还是靠脸吧</d><d p="31.72300,1,25,16777215,1598718868,0,3df82069,37526801400987655">加油</d><d p="28.66700,1,25,16777215,1598688414,0,ca9445dd,37510834626232323">本科交通工程</d><d p="738.71400,1,25,16777215,1598060864,0,4c910636,37181817659850757">that's actually ok</d><d p="21.75000,1,25,16777215,1597827320,0,741c55e5,37059373320110085">生物制药</d><d p="21.75000,1,25,16777215,1597827311,0,741c55e5,37059368855273475">生物制药</d><d p="515.55300,1,25,16777215,1597735030,0,b341e84e,37010987280760837">现在都是调用一下就可以了，除非你想到更牛逼的算法自己写库</d><d p="28.51900,1,25,16777215,1597567108,0,ee8227cf,36922947637608455">生物</d><d p="763.53900,5,25,16646914,1597481868,0,b99a5c6d,36878257011294213">吴老师鸡汤之日常安慰，大家不要走，听不懂就多听点</d><d p="25.70600,1,25,16777215,1597480852,0,b99a5c6d,36877724556984325">自动化</d><d p="368.33500,1,25,16777215,1597309150,0,1fae75d1,36787703413997575">别看不起专科各位</d><d p="273.75100,1,25,16777215,1597308994,0,1fae75d1,36787621221892103">富婆要求会ai的，所以我来学习了</d><d p="738.83300,1,25,16777215,1596932221,0,3467c167,36590084138467335">讲的好</d><d p="702.16300,1,25,16777215,1596881311,0,7a857d85,36563392531529731">那怎么判断是否收敛啊</d><d p="334.87600,1,25,16777215,1596880545,0,184fab6b,36562990624407555">就我一个高中生在这学机器学习吗？</d><d p="563.58900,1,25,16777215,1596871850,0,29f43338,36558432012075015">正则化通过加大惩罚项，解决过拟合，然后还解决了正规方程的可逆问题</d><d p="222.24300,1,25,16777215,1596871395,0,29f43338,36558193325244419">这都说的是default了，建议去重修英语四级</d><d p="35.57900,1,25,16777215,1596703218,0,4079cb79,36470020610457605">幼儿园大班，麻麻让我学一些简单的课外知识</d><d p="167.34000,1,25,16777215,1596621622,0,4cdaff1f,36427240785313799">这里不考虑1的输入嘛</d><d p="724.30600,1,25,16777215,1596615469,0,b7cbae70,36424014867988483">代价函数不止一种</d><d p="409.10600,1,25,16777215,1596542689,0,648dc235,36385857176338435">Java 永远的神</d><d p="24.57200,1,25,16777215,1596541860,0,648dc235,36385422151516163">物理</d><d p="576.16700,1,25,16777215,1596526830,0,17340ae0,36377542507626499">似曾相识图归来...</d><d p="45.08600,1,25,16777215,1596347253,0,68179a89,36283392029360135">开启第五个作业</d><d p="11.66800,5,25,16646914,1595947925,0,973c5451,36074029350125575">56/112</d><d p="18.74400,1,25,16777215,1595746031,0,a315fcf3,35968178677874691">自动化</d><d p="27.19200,1,25,16777215,1595347691,0,6ccb74c6,35759334073303043">数据科学专业</d><d p="752.25000,1,25,16777215,1595304492,0,e1f7ee93,35736684991610887">别信他的，大佬想骗咱们继续上课哈哈哈哈哈哈</d><d p="325.64100,1,25,16777215,1595303412,0,e1f7ee93,35736119106076675">python跑for循环太慢了</d><d p="751.11100,1,25,16777215,1594718543,0,69ba0582,35429478883131399">大佬我晕了</d><d p="49.33100,1,25,16777215,1594701031,0,a7e976ed,35420297873588227">奥里给</d><d p="0.00000,1,25,16777215,1594698863,0,b956488b,35419161290604549">一拳一个嘤嘤怪</d><d p="790.98500,1,25,16777215,1594386726,0,994591db,35255511326654471">吴老单边吃饭吗 脸歪了</d><d p="776.89200,1,25,16777215,1594369811,0,96e3458d,35246642984124423">这就是真正的学者专家吧</d><d p="740.26900,1,25,16777215,1594369770,0,96e3458d,35246621428023301">终于看完了这一章</d><d p="727.00300,1,25,16777215,1594369756,0,96e3458d,35246614475964421">耶</d><d p="562.03800,1,25,16777215,1594311101,0,23501a57,35215862290972675">这里咋就用平方差了，分类用的是cross entropy啊</d><d p="559.00400,1,25,16777215,1594194051,0,b59388c5,35154494267326467">正则化解决的不是过拟合问题吗</d><d p="759.37800,1,25,16777215,1594108866,0,e5a5ed9b,35109832546058243">混乱中</d><d p="330.50300,1,25,16777215,1594040570,0,a81a46dc,35074026118316039">你的高度决定富婆的富有度</d><d p="433.91600,1,25,16777215,1593913579,0,a7cf179c,35007446062202887">这个三角形delta为什么要累加啊，没搞明白</d><d p="28.82700,1,25,16777215,1593328730,0,d0488924,34700816717709319">MBIE</d><d p="283.61300,1,25,16777215,1592969156,0,4e81fe12,34512296302084163">好好学习，要啥自行车</d><d p="246.43600,1,25,16777215,1592923610,0,29320185,34488417188315141">憨憨</d><d p="726.82500,1,25,16777215,1592828034,0,3f6107dc,34438307778134021">amazing</d><d p="802.58500,1,25,16777215,1592728496,0,f9975e8d,34386121585065991">迷之微笑。</d><d p="351.01300,1,25,16777215,1592648187,0,7246164d,34344016202432517">有富婆吗，是在不行富豪也可以接受</d><d p="512.62500,1,25,16777215,1592568240,0,5e0ebb0a,34302100906180615">现在这些都有集成好的API直接可以调库了吧</d><d p="494.83900,1,25,16777215,1592531190,0,4b9dbc51,34282676133298179">我去看看鹿导</d><d p="764.96000,1,25,16777215,1592406681,0,a6ab14ab,34217397718089731">叶师傅：我都会一点</d><d p="775.47500,1,25,16777215,1592227368,0,742c255b,34123385972195331">《情商》</d><d p="430.65800,1,25,16777215,1592226793,0,742c255b,34123084289015813">不记得什么时候出现的这个公式了</d><d p="759.56800,1,25,16777215,1592042786,0,b10b4fe0,34026611994001415">日常安慰</d><d p="498.82100,1,25,16777215,1592041455,0,ab516041,34025914141507591">所以是梯度下降的每次跌打都要执行一遍之前的for 循环吗</d><d p="780.98100,1,25,16777215,1591957348,0,9e6f61f8,33981817884770307">又不用担心，我从头到现在不懂得都不用担心哈哈哈</d><d p="744.89100,1,25,16777215,1591957287,0,9e6f61f8,33981785640009797">是嘛，我咋看你讲的很轻松的样子，又想骗我继续学下去....</d><d p="708.00600,1,25,16777215,1591957075,0,9e6f61f8,33981674794516483">为啥不一定是正数？平方和还会出现负数吗？</d><d p="15.48200,1,25,16777215,1591815752,0,56859613,33907580373827587">问下各位都是什么专业的</d><d p="767.17700,1,25,16777215,1591088131,0,53dc64d5,33526097530322951">谢谢了谢谢了鼓励一波</d><d p="325.73000,1,25,16777215,1590920890,0,af2ad911,33438415185772549">富婆没有，男的也凑乎吧</d><d p="140.57900,1,25,16777215,1590908669,0,3939c4f5,33432007981662215">one hot编码</d><d p="761.24200,1,25,16777215,1590737660,0,c6197d9b,33342349836812293">大佬又谦虚了</d><d p="40.61700,1,25,16777215,1590648249,0,3a2b1469,33295472820486149">加油啊，米雨山</d><d p="759.94000,1,25,16777215,1590568560,0,83aab747,33253692843491395">大佬谦虚</d><d p="360.83800,1,25,16777215,1590472151,0,26d30b9c,33203146579247111">小学生来听听</d><d p="322.56500,1,25,16777215,1589977737,0,1c315f17,32943931148730371">更先进的向量表示方法 minipatch吧</d><d p="559.20500,1,25,16777215,1589768281,0,dca36827,32834115954278405">BP神经网络</d><d p="604.94700,1,25,16777215,1589450500,0,c3e0370b,32667507417415685">卡</d><d p="753.29300,1,25,16777215,1589447663,0,94bba085,32666020096770053">大佬说笑了</d><d p="393.71500,1,25,16777215,1589446628,0,94bba085,32665477133631491">奥利给</d><d p="756.24900,1,25,16777215,1589169183,0,c9e121b,32520016208855047">每节课的结尾老师都在actually ok</d><d p="793.45600,1,25,16777215,1589102656,0,b2634b65,32485137097687047">其实神经网络站在数学上是很好理解的hhhh大佬还是谦虚</d><d p="658.02300,1,25,16777215,1589102516,0,b2634b65,32485063609286661">matlab，for循环遍历就画出来了</d><d p="559.93100,1,25,16777215,1589102449,0,b2634b65,32485028486184967">正则化是解决overfit的</d><d p="515.95200,1,25,16777215,1589102395,0,b2634b65,32485000298889221">使用一次梯度检查的目的是确定你写的反向传播代码没有bug！！重复一次，梯度检查是确认你写的反向传播代码没有bug！</d><d p="368.52000,1,25,16777215,1589102279,0,b2634b65,32484939164286981">一个小小的补充，基本所有for循环都可以改写成向量化编程，以提高计算效率</d><d p="689.33700,1,25,16777215,1588903044,0,90289f5d,32380482829680645">可能是对数形式</d><d p="732.71600,1,25,16777215,1588133552,0,bf86d4b7,31977047194599431">123</d><d p="56.38000,1,25,16777215,1588082468,0,2734e1bb,31950264488951813">今天第一天，明天就可以看完所有的了</d><d p="562.12400,1,25,16777215,1587758640,0,372f0c7c,31780485328797701">正则化尽可能解决了过拟合</d><d p="50.30900,1,25,16777215,1587735467,0,2c534bf8,31768336347430915">我要三天看完剩下的视频</d><d p="787.00500,1,25,16777215,1587715658,0,e35ba8f5,31757950455906307">大佬：你心里好点没</d><d p="732.82100,1,25,16777215,1587615517,0,ba32d8cd,31705447733919749">现在还是散装的</d><d p="582.50100,1,25,16777215,1587615348,0,ba32d8cd,31705359206318087">听到这更晕了</d><d p="364.41800,1,25,16777215,1587534470,0,66d681e0,31662955839881219">我一个幼儿园的都来了你们怕啥</d><d p="383.85800,5,25,16765698,1587369597,0,e46d717b,31576514888204295">x是feed那y是...</d><d p="490.65500,1,25,16777215,1587218192,0,8dd979ee,31497134884257795">哈哈哈哈我去看看雨哥</d><d p="245.14400,1,25,16777215,1587186652,0,5856b884,31480598862757891">word2vec不是更小吗，， 相当于是压缩了编码</d><d p="760.55900,1,25,16777215,1587044927,0,e8a530a7,31406294335225859">又谦虚了</d><d p="134.81400,1,25,16777215,1586970932,0,d9092dbc,31367499350016003">实际上只有独热编码才有意义，其他编码实际上都得进行转换</d><d p="45.72200,1,25,16777215,1586970813,0,d9092dbc,31367437305774087">我要五天看完这个视频，这是第三天了</d><d p="359.13500,1,25,16777215,1586787304,0,7420f77f,31271225568264197">别放弃阿，毕竟富婆那么少，你们努力点让我分得一个</d><d p="487.36900,1,25,16777215,1586747368,0,fa6a0472,31250287506751493">我也去看看宝剑嫂</d><d p="754.79700,1,25,16777215,1586710084,0,7e32f6c4,31230739996475399">大佬太谦虚了</d><d p="664.24900,1,25,16777215,1586614179,0,8572425a,31180458133291013">同学，你前面没做作业啊</d><d p="437.69700,1,25,16777215,1586613937,0,8572425a,31180331480514565">大佬，写错了吧，索引是样本欸</d><d p="346.13100,1,25,16777215,1586613846,0,8572425a,31180283486142467">这个应该向量化就可以了吧</d><d p="233.51900,1,25,16777215,1586613620,0,8572425a,31180165200478211">还是不知道怎么选</d><d p="88.88700,1,25,16777215,1586613467,0,8572425a,31180084997521413">2020/04/11</d><d p="555.02700,1,25,16777215,1586443861,0,2e0bdfc2,31091162582351875">正则化不是已经解决局部最优的问题了吗？</d><d p="474.15000,1,25,16777215,1586425056,0,4da47994,31081303168253959">哈哈看了一个宝剑嫂的视频回来又听得下去了</d><d p="285.13300,1,25,16777215,1586400613,0,6d9e0429,31068488394604551">有没有那种能让我少奋斗二十年的女朋友</d><d p="375.57900,1,25,16777215,1586351739,0,293d470d,31042864291512387">怕不是竞赛大佬</d><d p="757.12000,1,25,16777215,1586351345,0,95820e35,31042657606172677">好了，大佬也不太懂，我不懂是应该的[狗头]</d><d p="15.00400,1,25,16777215,1585921708,0,cb59b8ff,30817404067512327">半山腰了，加油，奥里给！！！</d><d p="265.78300,5,25,52480,1585720369,0,977afb10,30711844179542019">要是有fp我还在这学？</d><d p="266.67400,1,25,16777215,1585556149,0,8b385564,30625745850073095">我也不想努力了 求介绍cs大佬</d><d p="762.50800,1,25,16777215,1585494205,0,edbd942d,30593269476360197">又在忽悠我们</d><d p="525.52400,1,25,16777215,1585466201,0,9341e67d,30578587209302021">zji</d><d p="754.09200,1,25,16777215,1585453274,0,93c9d79e,30571809638187013">大佬太会安慰人了</d><d p="754.09200,1,25,16777215,1585453262,0,93c9d79e,30571803455258631">大佬又谦虚了</d><d p="684.42100,1,25,16777215,1585397151,0,8ae6c95d,30542385385046023">代价函数再怎么也不能是负的呀……</d><d p="269.98100,1,25,16777215,1585396583,0,8ae6c95d,30542087127040005">少玩游戏多看书，少生孩子多养猪</d><d p="753.87300,1,25,16777215,1585380770,0,dc83726,30533796483301379">阳光养猪场</d><d p="763.58400,1,25,16777215,1585294524,0,bd033357,30488579196583941">我忍不住法第三名了</d><d p="749.84800,1,25,16777215,1585287248,0,dd9c9e24,30484764119531527">..............</d><d p="287.27400,1,25,16777215,1585188047,0,4033db9,30432754635636743">就没女生么。。都想找富婆</d><d p="363.23500,1,25,16777215,1585031965,0,aae1e256,30350922506305541">我刚满月，就来学这个</d><d p="271.25500,1,25,16777215,1585031856,0,aae1e256,30350865471111173">富婆也是有标准的</d><d p="763.39500,1,25,16777215,1584898046,0,e20dbbf8,30280710546259975">老师贼会鼓励人</d><d p="742.39800,1,25,16777215,1584676976,0,9bb38582,30164805980520455">日常谦虚</d><d p="756.06500,1,25,16777215,1584592213,0,45ddfd76,30120365620461571">大佬:不太了解=了解了200%</d><d p="752.72600,1,25,16777215,1584525060,0,e43db49b,30085158148243461">研一听得一知半解</d><d p="251.56900,1,25,16777215,1584366769,0,82119ce1,30002168230051847">居然还在继续....</d><d p="15.10900,1,25,16777215,1584363961,0,82119ce1,30000695823302659">终于一半了，太难了</d><d p="32.49700,1,25,16777215,1584355030,0,c6a9f6a4,29996013659357189">加油，兄弟们</d><d p="778.24300,1,25,16777215,1584344782,0,4c480781,29990640593928197">咋走了一个</d><d p="27.47200,1,25,16777215,1584187882,0,14b0bb5c,29908379820883973">加油</d><d p="363.77800,1,25,16777215,1584173990,0,48e5ce8f,29901096474378243">我小学二年级也来听听</d><d p="363.83600,1,25,16777215,1584101775,0,a971031,29863235107160069">高中生是认真的吗 听到这里</d><d p="741.13300,1,25,16777215,1584071102,0,4a7ceec4,29847153602985987">大二听的一知半解</d><d p="511.16700,1,25,16777215,1584043862,0,b4b40f99,29832872071266309">应该是对所有训练集使用一次反向传播，，用梯度检测确定能够算出正确的偏导就关，然后再不停迭代反向传播，更新参数，直到收敛</d><d p="775.61500,1,25,16777215,1584019228,0,4846abc1,29819956610727941">大佬：其实我都知道</d><d p="760.66500,1,25,16777215,1583999624,0,1c7851dc,29809678337703941">越厉害的人越谦虚，因为越厉害越知道自己未知的还太多</d><d p="697.00800,1,25,16777215,1583999462,0,1c7851dc,29809593515769863">梯度不就是偏导数吗</d><d p="650.14200,1,25,16777215,1583999409,0,1c7851dc,29809565896278021">有个疑问，这个图是怎么出来的？用一堆theta画出来的？那这个范围怎么取？</d><d p="767.00300,1,25,16777215,1583674681,0,30a5c70c,29639314974965765">您太谦虚了</d><d p="334.15800,1,25,16777215,1583634477,0,483b0203,29618236321955847">少奋斗几十年，</d><d p="323.86800,1,25,16777215,1583634435,0,483b0203,29618214522060805">学历高遇见富婆概率大</d><d p="319.34800,1,25,16777215,1583634385,0,483b0203,29618188240027653">有富婆吗？想少奋斗几十年</d><d p="747.02300,1,25,16777215,1583584538,0,9534404f,29592053770878983">的确有点片段没懂</d><d p="507.42600,1,25,16777215,1583566039,0,828c7de2,29582354835046405">应该是训练完了在关</d><d p="34.63400,1,25,16777215,1583565519,0,828c7de2,29582082496790535">我两天到这里了</d><d p="747.87900,1,25,16777215,1583554314,0,efa650f0,29576207649472517">？？？</d><d p="128.50400,1,25,16777215,1583488929,0,c1c67cd3,29541927396835333">one hot 编码</d><d p="357.18900,1,25,16777215,1583413766,0,bb81a75,29502520207867909">高中生来听听</d><d p="239.97300,1,25,16777215,1583396062,0,763e8959,29493238274981895">差点以为这个视频结束了</d><d p="441.49000,1,25,16777215,1583308321,0,1e03456,29447236377640967">听不下去了</d><d p="116.11700,1,25,16777215,1583151452,0,a53e153d,29364991894224901">one-hot编码</d><d p="765.57200,1,25,16777215,1583140306,0,224a4940,29359148487933955">大佬太谦虚了</d><d p="51.90700,1,25,16776960,1583124292,0,4c5011fb,29350752271466501">114514</d><d p="23.34700,1,25,16777215,1583124062,0,4c5011fb,29350631953661959">加油啊，米娜桑</d><d p="751.27500,1,25,16777215,1583055920,0,b20c73df,29314905692176387">大佬又在谦虚了</d><d p="350.90100,1,25,16777215,1583055345,0,b20c73df,29314604165758979">专科+1</d><d p="554.12000,1,25,16777215,1582939121,0,51332b98,29253669758173251">这里用的是平方差</d><d p="283.29100,1,25,16777215,1582530796,0,c93e9e5a,29039589616254979">我身体好，求多介绍几个</d><d p="762.30900,1,25,16777215,1582443914,0,7d581458,28994038718791680">大佬有鸡汤了</d><d p="255.37900,1,25,16777215,1582443161,0,7d581458,28993643908431872">一枪一个嘤嘤怪</d><d p="11.77900,1,25,16777215,1582440710,0,7d581458,28992358603292674">已经一般啦</d><d p="767.67800,1,25,16777215,1582364964,0,3a9b844d,28952645833064448">大佬总是很谦虚</d><d p="201.33700,1,25,16777215,1582363281,0,99328711,28951763349405700">翻译的有问题，人家说的是is a good thing</d><d p="25.18900,1,25,16777215,1582180737,0,51343458,28856057900040192">还有一半</d><d p="769.76900,1,25,16777215,1582026073,0,b281feed,28774969625280516">王者的话术</d><d p="692.06500,1,25,16777215,1581846330,0,ded1e0ce,28680732096856064">有了偏导数就有了梯度 第一个想到这个的人真是厉害啊</d><d p="347.87700,1,25,16777215,1581844752,0,ded1e0ce,28679905076051968">各位大佬淡定  我一个专科生还能看到这里你们怕啥</d><d p="272.74900,1,25,16777215,1581297833,0,c8e28768,28393162143694850">我还想挣扎挣扎，毕竟身体不好</d><d p="671.70200,1,25,16777215,1581050220,0,9c0b60dd,28263341380075524">這張圖上 應該是要看接近0的位置而不是最低的地方...吧</d><d p="705.45000,1,25,16777215,1580967607,0,6ccb8d0b,28220028377628674">值最小，并不一定是正数</d><d p="76.44100,1,25,16777215,1580964016,0,6ccb8d0b,28218145933099008">2020，2.6 武汉加油</d><d p="252.47700,1,25,16777215,1580963319,0,7050d9f,28217780403699712">一拳一个嘤嘤怪</d><d p="275.78400,1,25,16777215,1580909449,0,23aa90ef,28189536773734400">你长得好看吗</d><d p="671.97000,1,25,16777215,1580293921,0,b83877ee,27866822974373888">一般代价函数不会取到负的,前面是这个意思吗</d><d p="551.69400,1,25,16777215,1580284447,0,b83877ee,27861855840501762">逻辑回归的代价函数我记得是凸函数呀</d><d p="797.97500,1,25,16777215,1580106100,0,536a52ce,27768350598758400">这老师太温柔了</d><d p="732.17900,1,25,16777215,1580106034,0,536a52ce,27768316092219392">讲得太好了</d><d p="761.96200,1,25,16777215,1579767965,0,f5662250,27591070202200068">卖弱啊</d><d p="376.30300,1,25,16777215,1579338814,0,c78333fc,27366071932026884">喂（feed）这个字，用的好</d><d p="152.77300,1,25,16777215,1579334228,0,c78333fc,27363667366903808">这个最后应该是通过inde获取分类类别的。。</d><d p="62.40500,1,25,16777215,1579334013,0,c78333fc,27363554453094404">iOS飘过</d><d p="768.47400,1,25,16777215,1579331463,0,348f95df,27362217735749636">大佬的嘴，骗人的鬼</d><d p="9.69200,1,25,16777215,1578998814,0,f0c454b8,27187814064455680">终于刷了一半了 太南了</d><d p="286.26200,1,25,16646914,1578216221,0,13d6dfae,26777509438160900">那我就求介绍10个富婆吧</d><d p="67.06000,1,25,16777215,1577706428,0,a51f8fa0,26510231460642818">12.30</d><d p="758.54500,1,25,16777215,1576844636,0,e6403e27,26058403951411264">大佬还算成功，那其他人就只能是失败了呀，太谦虚了，哈哈哈</d><d p="65.33900,1,25,16777215,1576495015,0,e24f4f29,25875102030626820">191216</d><d p="577.34700,1,25,52480,1575700685,0,be52a5b4,25458644123910144">靠自己年轻？</d><d p="120.51400,1,25,16777215,1575699517,0,be52a5b4,25458032198549508">还是养猪好啊</d><d p="15.73700,1,25,16777215,1575528310,0,b84d1dda,25368270465925120">加油啊，小鱼儿</d><d p="481.24500,1,25,16777215,1574946765,0,170fa258,25063373249445890">是检查一次就关掉吗？</d><d p="166.19500,1,25,16777215,1574946240,0,170fa258,25063097835716608">什么逻辑死？</d><d p="330.93000,1,25,16777215,1574674383,0,1ee2370,24920566439870464">研究生？？？大一萌新瑟瑟发抖</d><d p="771.28000,1,25,16777215,1574501977,0,489d7493,24830176309805060">又安慰我</d><d p="59.42900,1,25,16777215,1574343865,0,8e55cc8f,24747279957098498">我是做网络的</d><d p="322.41000,1,25,16777215,1574170060,0,67503c8f,24656156369616896">我为啥要读研</d><d p="772.45000,1,25,16777215,1573891487,0,9424de22,24510103707713536">男人的嘴，骗人的鬼</d><d p="160.58800,1,25,16777215,1573318024,0,dd032886,24209443724984322">前面的、不建议这样、可以从逻辑死地的角度考虑</d><d p="266.76800,1,25,16777215,1573130892,0,b21fe19e,24111332878450688">给我也介绍一个吧，富婆抱抱我</d><d p="756.67400,1,25,16777215,1573108689,0,8d3dfc02,24099692049072132">大佬又在安慰人</d><d p="769.75900,1,25,16777215,1572654797,0,b40184c,23861721790676994">太谦虚了</d><d p="765.14300,1,25,16777215,1572272496,0,5b2c9905,23661285941968900">骗人的嘴</d><d p="74.29000,1,25,16777215,1572229746,0,db898792,23638872460623876">19/10/28</d><d p="680.65500,1,25,16777215,1571562014,0,bd74a969,23288788646625280">哈哈哈，楼上好眼力</d><d p="317.03200,1,25,16777215,1571399172,0,4f463abb,23203412906606592">大型弃学现场</d><d p="149.92400,1,25,16777215,1570958261,0,1963f9db,22972248486838274">可以有四个输出单元么，二进制的话，就可以表示16个分类</d><d p="270.22000,1,25,16777215,1570936732,0,2ff39599,22960961059553280">我要是认识富婆，还用在这努力?</d><d p="754.93100,1,25,16777215,1570781637,0,f287d22d,22879646633164802">又谦虚了</d><d p="246.63400,1,25,16777215,1570781031,0,f287d22d,22879328665075716">嘤嘤嘤</d><d p="315.57200,1,25,16777215,1570763667,0,792716ee,22870224906747904">又没人逼着你学</d><d p="768.06100,1,25,16777215,1570723443,0,3136e7bb,22849136142319616">又在安慰大家</d><d p="188.79900,1,25,16777215,1570636465,0,7c24ef0a,22803534571896836">说了是通常情况下是第一个</d><d p="245.84200,1,25,16777215,1570004179,0,a558f6d4,22472034639937540">嘤嘤嘤novation</d><d p="667.40300,1,25,16777215,1569578866,0,abdb7ef2,22249048280924160">图上圈出来的点，J函数值看上去都快到-2了</d><d p="32.99000,1,25,16777215,1567840407,0,58f0a5de,21337595100790788">做作业卡住了，再来复习一下</d><d p="322.79000,1,25,16777215,1567346247,0,b19bc5c6,21078512719888384">那给我介绍个富婆和富豪吧</d><d p="191.28500,1,25,16777215,1566975422,0,65e85907,20884093867130880">Default是默认，你自己决定，不绝对</d><d p="314.82200,1,25,16777215,1566889506,0,d992b9a9,20839048697348098">靠天靠地不如靠自己</d><d p="288.61900,1,25,16777215,1566889479,0,d992b9a9,20839034966245376">随机初始化权重，前向传播，计算代价函数，反向传播</d><d p="196.21100,1,25,16777215,1566889329,0,d992b9a9,20838956315181056">默认选项</d><d p="5.78900,1,25,16777215,1566889139,0,d992b9a9,20838856471871490">还有好多，呜呜呜</d><d p="50.22400,1,25,16777215,1566203324,0,2f49ac8e,20479291703689220">你们是AI吗</d><d p="73.22100,1,25,16777215,1566072267,0,58f0a5de,20410580237025284">19817</d><d p="48.36000,1,25,16777215,1566072226,0,58f0a5de,20410558890115074">有人啊</d><d p="68.40300,1,25,16777215,1565795692,0,2dd91ab5,20265575260880896">19814</d><d p="332.80100,1,25,16777215,1565244439,0,7a0a5e2d,19976560207986690">坚持住啊 同学们</d><d p="299.02100,1,25,16777215,1565164247,0,e14edc2b,19934516614266880">学不下去了，</d><d p="296.13000,1,25,16777215,1565164227,0,e14edc2b,19934506113826816">前方高能预警</d><d p="310.34000,1,25,16777215,1565163944,0,83a39619,19934357612396544">我只要有个能吃能躺的住处就好</d><d p="64.90300,1,25,16777215,1565163657,0,83a39619,19934206908956672">1987</d><d p="49.27300,1,25,16777215,1565163641,0,83a39619,19934198701752320">阵亡了</d><d p="278.50600,1,25,16777215,1565063131,0,b56f5475,19881502415781888">那我就求介绍个富豪吧</d><d p="56.89000,1,25,16777215,1565062177,0,b56f5475,19881002161668100">19.8.6</d><d p="263.74600,1,25,16777215,1564388612,0,f2ee93ec,19527860459405314">各位，我不想努力了，求介绍富婆</d><d p="186.54100,1,25,16777215,1564237482,0,c598a0ec,19448624434905088">这个不是绝对的吧</d><d p="44.61200,1,25,16777215,1564237248,0,c598a0ec,19448502155739138">有啊</d><d p="242.90900,1,25,16777215,1562988080,0,a7896662,18793577908797440">嘤嘤嘤嘤嘤嘤</d><d p="232.17800,1,25,16777215,1562988069,0,a7896662,18793572361306114">嘤嘤嘤</d><d p="185.54400,1,25,16777215,1562988022,0,a7896662,18793547962515458">每个隐藏层的神经元个数相同</d><d p="126.11300,1,25,16777215,1562987963,0,a7896662,18793516749553668">0000100</d><d p="104.99300,1,25,16777215,1562987942,0,a7896662,18793505684979714">输出成向量</d><d p="52.64000,1,25,16777215,1562987890,0,a7896662,18793478286737408">专心听讲</d><d p="49.06700,1,25,16777215,1562520170,0,211fadff,18548258574434306">有啊</d><d p="41.00600,1,25,16777215,1559007427,0,7291e383,16706569653190658">没人</d></i>